ootrain/__init__.py
ootrain-0.0.1.dist-info/METADATA
ootrain-0.0.1.dist-info/WHEEL
ootrain-0.0.1.dist-info/top_level.txt
ootrain-0.0.1.dist-info/RECORD
