Metadata-Version: 2.4
Name: ootrain
Version: 0.0.1
Summary: ootrain
Author: abhishek
Project-URL: Homepage, https://github.com/abhishekkrthakur/ootrain
Project-URL: Issues, https://github.com/abhishekkrthakur/ootrain/issues
Keywords: ootrain
Classifier: Development Status :: 5 - Production/Stable
Classifier: License :: OSI Approved :: Apache Software License
Classifier: Operating System :: OS Independent
Classifier: Programming Language :: Python :: 3.10
Classifier: Programming Language :: Python :: 3.11
Classifier: Topic :: Scientific/Engineering :: Artificial Intelligence
